tinytool/NetTools.py
tinytool/XlsxTools.py
tinytool/__init__.py
tinytool-0.1.8.dist-info/LICENSE
tinytool-0.1.8.dist-info/METADATA
tinytool-0.1.8.dist-info/WHEEL
tinytool-0.1.8.dist-info/top_level.txt
tinytool-0.1.8.dist-info/RECORD
