Metadata-Version: 2.1
Name: tinytool
Version: 0.1.8
Summary: A tiny tool for personal use
Home-page: https://github.com/leeHeisen/TinyTool.git
Author: leeheisen
Author-email: leeheisen@126.com
License: UNKNOWN
Project-URL: Bug Tracker, https://github.com/leeHeisen/TinyTool/issues
Platform: UNKNOWN
Classifier: Programming Language :: Python :: 3
Classifier: License :: OSI Approved :: MIT License
Classifier: Operating System :: OS Independent
Requires-Python: >=3.6
Requires-Dist: xlwings
Requires-Dist: json5
Requires-Dist: pytz
